MANIFEST.in
README.md
setup.py
addresscleaner/__init__.py
addresscleaner/us_states.py
addresscleaner.egg-info/PKG-INFO
addresscleaner.egg-info/SOURCES.txt
addresscleaner.egg-info/dependency_links.txt
addresscleaner.egg-info/top_level.txt