Metadata-Version: 1.0
Name: addresscleaner
Version: 0.0.4
Summary: Utility for normalizing (Prisoner-centric) street addresses
Home-page: https://github.com/yourcelf/btb-address-cleaner
Author: Charlie DeTar
Author-email: cfd@media.mit.edu
License: BSD
Platform: UNKNOWN
